Workbook

Sheet Categories
A1: Category_ID | B1: Category_Name
A2: 1 | B2: Food
A3: 2 | B3: Transport
A4: 3 | B4: Rent
A5: 4 | B5: Shopping
A6: 5 | B6: Entertainment
A7: 6 | B7: Medical
A8: 7 | B8: Education
A9: 8 | B9: Other

Sheet Income
A1: Date | B1: Source | C1: Amount
A2: 46023 | B2: Salary | C2: 30000
A3: 46143 | B3: Freelance | C3: 5000

Sheet Expenses
A1: Date | B1: Category | C1: Description | D1: Amount | E1: Month
A2: 46174 | B2: Food | C2: Lunch | D2: 150 | E2: =TEXT(A2,"mmm") -> Jun
A3: 46059 | B3: Food | C3: Dinner | D3: 300 | E3: =TEXT(A3,"mmm") -> Feb
A4: 46059 | B4: Transport | C4: Bus | D4: 40 | E4: =TEXT(A4,"mmm") -> Feb
A5: 46148 | B5: Shopping | C5: Clothes | D5: 1500 | E5: May
A6: 46362 | B6: Education | C6: Online course | D6: 1200 | E6: Dec
A7: 46252 | B7: Medical | C7: Medicines | D7: 250 | E7: Aug
A8: 46034 | B8: Entertainment | C8: Movie | D8: 300 | E8: Jan
A9: 46301 | B9: Rent | C9: House rent | D9: 8000 | E9: Oct

Sheet Budget
A1: Category | B1: Monthly_Budget
A2: Food | B2: 4000
A3: Transport | B3: 1500
A4: Rent | B4: 8000
A5: Shopping | B5: 3000
A6: Entertainment | B6: 2000
A7: Medical | B7: 1000
A8: Education | B8: 2000
A9: Other | B9: 1500

Sheet Summary
A1: Total Income | B1: =SUM(Income!C:C) -> 35000
A2: Total Expense | B2: =SUM(Expenses!D:D) -> 11740
A3: Savings | B3: =B1-B2 -> 23260
A6: Category | B6: Total Spent | D6: Category | E6: Budget | F6: Spent | G6: Balance
A7: Food | B7: =SUMIFS(Expenses!D:D, Expenses!B:B, A7) -> 450 | D7: Food | E7: =VLOOKUP(D7, Budget!A:B, 2, FALSE) -> 4000 | F7: =SUMIFS(Expenses!D:D, Expenses!B:B, D7) -> 450 | G7: =E7-F7 -> 3550
A8: Transport | B8: =SUMIFS(Expenses!D:D, Expenses!B:B, A8) -> 40 | D8: Transport | E8: =VLOOKUP(D8, Budget!A:B, 2, FALSE) -> 1500 | F8: =SUMIFS(Expenses!D:D, Expenses!B:B, D8) -> 40 | G8: =E8-F8 -> 1460
A9: Rent | B9: =SUMIFS(Expenses!D:D, Expenses!B:B, A9) -> 8000 | D9: Rent | E9: =VLOOKUP(D9, Budget!A:B, 2, FALSE) -> 8000 | F9: =SUMIFS(Expenses!D:D, Expenses!B:B, D9) -> 8000 | G9: =E9-F9 -> 0
A10: Shopping | B10: =SUMIFS(Expenses!D:D, Expenses!B:B, A10) -> 1500 | D10: Shopping | E10: =VLOOKUP(D10, Budget!A:B, 2, FALSE) -> 3000 | F10: =SUMIFS(Expenses!D:D, Expenses!B:B, D10) -> 1500 | G10: =E10-F10 -> 1500
A11: Entertainment | B11: =SUMIFS(Expenses!D:D, Expenses!B:B, A11) -> 300 | D11: Entertainment | E11: =VLOOKUP(D11, Budget!A:B, 2, FALSE) -> 2000 | F11: =SUMIFS(Expenses!D:D, Expenses!B:B, D11) -> 300 | G11: =E11-F11 -> 1700
A12: Medical | B12: =SUMIFS(Expenses!D:D, Expenses!B:B, A12) -> 250 | D12: Medical | E12: =VLOOKUP(D12, Budget!A:B, 2, FALSE) -> 1000 | F12: =SUMIFS(Expenses!D:D, Expenses!B:B, D12) -> 250 | G12: =E12-F12 -> 750
A13: Education | B13: =SUMIFS(Expenses!D:D, Expenses!B:B, A13) -> 1200 | D13: Education | E13: =VLOOKUP(D13, Budget!A:B, 2, FALSE) -> 2000 | F13: =SUMIFS(Expenses!D:D, Expenses!B:B, D13) -> 1200 | G13: =E13-F13 -> 800
A14: other | B14: =SUMIFS(Expenses!D:D, Expenses!B:B, A14) -> 0 | D14: other | E14: =VLOOKUP(D14, Budget!A:B, 2, FALSE) -> 1500 | F14: =SUMIFS(Expenses!D:D, Expenses!B:B, D14) -> 0 | G14: =E14-F14 -> 1500
G19: Month | H19: Total Expense
G20: Jan | H20: =SUMIFS(Expenses!D:D, Expenses!E:E, G20) -> 300 | J20: Month | K20: Income | L20: Expense | M20: Savings
G21: Feb | H21: =SUMIFS(Expenses!D:D, Expenses!E:E, G21) -> 340 | J21: Jan | K21: =$B$1 -> 35000 | L21: =H21 -> 340 | M21: =K21 - L21 -> 34660
G22: Mar | H22: =SUMIFS(Expenses!D:D, Expenses!E:E, G22) -> 0 | J22: Feb | K22: =$B$1 -> 35000 | L22: =H22 -> 0 | M22: =K22 - L22 -> 35000
G23: Apr | H23: =SUMIFS(Expenses!D:D, Expenses!E:E, G23) -> 0 | J23: Mar | K23: =$B$1 -> 35000 | L23: =H23 -> 0 | M23: =K23 - L23 -> 35000
G24: May | H24: =SUMIFS(Expenses!D:D, Expenses!E:E, G24) -> 1500 | J24: Apr | K24: =$B$1 -> 35000 | L24: =H24 -> 1500 | M24: =K24 - L24 -> 33500
G25: Jun | H25: =SUMIFS(Expenses!D:D, Expenses!E:E, G25) -> 150 | J25: May | K25: =$B$1 -> 35000 | L25: =H25 -> 150 | M25: =K25 - L25 -> 34850
G26: Jul | H26: =SUMIFS(Expenses!D:D, Expenses!E:E, G26) -> 0 | J26: Jun | K26: =$B$1 -> 35000 | L26: =H26 -> 0 | M26: =K26 - L26 -> 35000
G27: Aug | H27: =SUMIFS(Expenses!D:D, Expenses!E:E, G27) -> 250 | J27: Jul | K27: =$B$1 -> 35000 | L27: =H27 -> 250 | M27: =K27 - L27 -> 34750
G28: Sep | H28: =SUMIFS(Expenses!D:D, Expenses!E:E, G28) -> 0 | J28: Aug | K28: =$B$1 -> 35000 | L28: =H28 -> 0 | M28: =K28 - L28 -> 35000
G29: Nov | H29: =SUMIFS(Expenses!D:D, Expenses!E:E, G29) -> 0 | J29: Sep | K29: =$B$1 -> 35000 | L29: =H29 -> 0 | M29: =K29 - L29 -> 35000
G30: Dec | H30: =SUMIFS(Expenses!D:D, Expenses!E:E, G30) -> 1200 | J30: Oct | K30: =$B$1 -> 35000 | L30: =H30 -> 1200 | M30: =K30 - L30 -> 33800
J31: Nov | K31: =$B$1 -> 35000 | L31: =H31 | M31: =K31 - L31 -> 35000
J32: Dec | K32: =$B$1 -> 35000 | L32: =H32 | M32: =K32 - L32 -> 35000

Sheet Dashboard
